tlnetcard_python/__init__.py
tlnetcard_python/login.py
tlnetcard_python/device/__init__.py
tlnetcard_python/monitor/__init__.py
tlnetcard_python/monitor/about/__init__.py
tlnetcard_python/monitor/about/information/__init__.py
tlnetcard_python/monitor/about/information/information.py
tlnetcard_python/monitor/environment/__init__.py
tlnetcard_python/monitor/environment/configuration/__init__.py
tlnetcard_python/monitor/environment/configuration/configuration.py
tlnetcard_python/monitor/history/__init__.py
tlnetcard_python/monitor/history/configure/__init__.py
tlnetcard_python/monitor/history/configure/configure.py
tlnetcard_python/monitor/history/data_log/__init__.py
tlnetcard_python/monitor/history/data_log/data_log.py
tlnetcard_python/monitor/history/event_log/__init__.py
tlnetcard_python/monitor/history/event_log/event_log.py
tlnetcard_python/monitor/information/__init__.py
tlnetcard_python/monitor/information/information.py
tlnetcard_python/monitor/information/battery_parameters/__init__.py
tlnetcard_python/monitor/information/battery_parameters/battery_parameters.py
tlnetcard_python/monitor/information/identification/__init__.py
tlnetcard_python/monitor/information/identification/identification.py
tlnetcard_python/monitor/information/in_out_parameters/__init__.py
tlnetcard_python/monitor/information/in_out_parameters/in_out_parameters.py
tlnetcard_python/monitor/information/shutdown_agent/__init__.py
tlnetcard_python/monitor/information/shutdown_agent/shutdown_agent.py
tlnetcard_python/monitor/information/status_indication/__init__.py
tlnetcard_python/monitor/information/status_indication/status_indication.py
tlnetcard_python/monitor/information/ups_properties/__init__.py
tlnetcard_python/monitor/information/ups_properties/ups_properties.py
tlnetcard_python/system/__init__.py
tlnetcard_python/system/administration/__init__.py
tlnetcard_python/system/administration/batch_configuration/__init__.py
tlnetcard_python-0.3.3.dist-info/LICENSE
tlnetcard_python-0.3.3.dist-info/METADATA
tlnetcard_python-0.3.3.dist-info/WHEEL
tlnetcard_python-0.3.3.dist-info/top_level.txt
tlnetcard_python-0.3.3.dist-info/RECORD
