Metadata-Version: 2.1
Name: tlnetcard-python
Version: 0.3.3
Summary: A Python 3 API for Tripp Lite's TLNETCARD.
Home-page: https://github.com/EGuthrieWasTaken/tlnetcard_python
Author: Ethan Guthrie
Author-email: guthrieec@cofc.edu
License: GNU GPLv3
Platform: UNKNOWN
Classifier: Development Status :: 2 - Pre-Alpha
Classifier: Programming Language :: Python
Classifier: Programming Language :: Python :: 3 :: Only
Classifier: Programming Language :: Python :: 3.5
Classifier: Programming Language :: Python :: 3.6
Classifier: Programming Language :: Python :: 3.7
Classifier: Programming Language :: Python :: 3.8
Classifier: License :: OSI Approved :: GNU General Public License v3 (GPLv3)
Classifier: Intended Audience :: Information Technology
Classifier: Topic :: System :: Power (UPS)
Requires-Python: >=3.5
Requires-Dist: pysnmp (==4.4.12)
Requires-Dist: requests (==2.23.0)
Requires-Dist: selenium (==3.141.0)
Requires-Dist: typing (==3.7.4.1)
